mpo/__init__.py
mpo/__main__.py
mpo/links.py
mpo/pdf.py
mpo/show.py
mpo_oze-0.2.1.dist-info/LICENSE
mpo_oze-0.2.1.dist-info/METADATA
mpo_oze-0.2.1.dist-info/WHEEL
mpo_oze-0.2.1.dist-info/entry_points.txt
mpo_oze-0.2.1.dist-info/top_level.txt
mpo_oze-0.2.1.dist-info/RECORD
