Metadata-Version: 2.1
Name: mpo-oze
Version: 0.2.1
Summary: Parse reports covering renewables published by the Czech Ministry of Trade and Industry
Home-page: https://github.com/jandolezal/mpo-oze
Author: Jan Doležal
Author-email: aswlk2zn2@mozmail.com
License: MIT
Platform: UNKNOWN
Classifier: License :: OSI Approved :: MIT License
Classifier: Programming Language :: Python :: 3
Classifier: Operating System :: OS Independent
License-File: LICENSE
Requires-Dist: beautifulsoup4
Requires-Dist: camelot-py[base]
Requires-Dist: requests
